lab1/vending_machine/change_state.v
`include "vending_machine_def.v"


module change_state(clk,reset_n,current_total_nxt,current_total);

	input clk;
	input reset_n;
	input [`kTotalBits-1:0] current_total_nxt;
	output reg [`kTotalBits-1:0] current_total;
	
	// Sequential circuit to reset or update the states
	always @(posedge clk) begin
		if (!reset_n) begin
			// TODO: reset all states.
			current_total <= 0;
		end 
		else begin
			// TODO: update all states.
			current_total <= current_total_nxt;
		end
	end


endmodule

lab1/vending_machine/calculate_current_state.v

`include "vending_machine_def.v"
	

module calculate_current_state(i_input_coin,i_select_item,item_price,coin_value,current_total,
input_total, output_total, current_total_nxt,o_available_item,o_output_item);

	input [`kNumCoins-1:0] i_input_coin;
	input [`kNumItems-1:0]	i_select_item;			
	input [31:0] item_price [`kNumItems-1:0];
	input [31:0] coin_value [`kNumCoins-1:0];	
	input [`kTotalBits-1:0] current_total;
	output reg [`kNumItems-1:0] o_available_item,o_output_item;
	output reg  [`kTotalBits-1:0] input_total, output_total,current_total_nxt;
	
	integer i;

	always @(*) begin
		
		input_total = 0;
		
		for(i=0; i < `kNumCoins; i = i + 1)
			input_total = input_total + i_input_coin[i] * coin_value[i];

	end

	always @(*) begin
		o_available_item = 0;

		for(i = 0; i < `kNumItems; i = i + 1) 
			o_available_item[i] = item_price[i] <= current_total ? 1 : 0;
	end

	always @(i_select_item, o_available_item) begin

		output_total = 0;
		o_output_item = 0;
		

		for(i = 0; i < `kNumItems; i = i + 1) begin

			if(i_select_item[i] & o_available_item[i]) begin
				o_output_item[i] = 1;
			end	else begin
				o_output_item[i] = 0;
			end

			output_total = output_total + item_price[i] * o_output_item[i];

		end

	end

	always @(*)
		current_total_nxt = current_total + input_total - output_total;

endmodule

lab1/vending_machine/check_time_and_coin.v
`include "vending_machine_def.v"

module check_time_and_coin(i_input_coin,i_select_item,clk,reset_n,o_output_item,i_trigger_return
,coin_value,current_total,o_return_coin,return_total,wait_time);
	input clk;
	input reset_n;
	input [`kNumCoins-1:0] i_input_coin;
	input [`kNumItems-1:0]	i_select_item;
	input [`kNumItems-1:0] o_output_item;
	input i_trigger_return;
	input [31:0] coin_value [`kNumCoins-1:0];
	input [`kTotalBits-1:0] current_total;
	output reg  [`kNumCoins-1:0] o_return_coin;
	output reg [`kTotalBits-1:0] return_total;
	output reg [31:0] wait_time;

	reg [`kTotalBits-1:0] left_coin;
	integer i;

	// initiate values
	initial begin
		// TODO: initiate values
		o_return_coin = 0;
		wait_time = 0;
	end

	always @(*) begin
		// TODO: o_return_coin & return_total
		o_return_coin = 0;
		return_total = 0;
		left_coin = 0;

		if(wait_time == 0 || i_trigger_return) begin

			return_total = current_total;
			
			for(i = 2; i >= 0; i--) begin
				
				if(current_total - left_coin >= coin_value[i]) begin
					
					o_return_coin[i] = 1;
					left_coin += (current_total - left_coin) / coin_value[i] * coin_value[i];

				end else
					o_return_coin[i] = 0;

			end
			
		end else begin
			o_return_coin = 0;
			return_total = 0;
		end
		

	end

	always @(posedge clk) begin
		if (!reset_n) begin
		// TODO: reset all states.
			wait_time = 0;
			o_return_coin = 0;
		end else if(i_input_coin || o_output_item)
			// initiate
			wait_time = `kWaitTime;
		else begin
		// TODO: update all states.
			if(wait_time > 1) 
				wait_time = wait_time - 1;
			else
				wait_time = 0;
		end
		

	end

endmodule

lab1/vending_machine/vending_machine.v
// Title         : vending_machine.v
// Author      : Jae-Eon Jo (Jojaeeon@postech.ac.kr) 
//			     Dongup Kwon (nankdu7@postech.ac.kr) (2015.03.30)
//			     Jaehun Ryu (jaehunryu@postech.ac.kr) (2021.03.07)

`include "vending_machine_def.v"


module vending_machine (
	clk,							// Clock signal
	reset_n,						// Reset signal (active-low)

	i_input_coin,				// coin is inserted.
	i_select_item,				// item is selected.
	i_trigger_return,			// change-return is triggered 

	o_available_item,			// Sign of the item availability
	o_output_item,			// Sign of the item withdrawal
	o_return_coin				// Sign of the coin return
);

	// Ports Declaration
	// Do not modify the module interface
	input clk;
	input reset_n;
	
	input [`kNumCoins-1:0] i_input_coin;
	input [`kNumItems-1:0] i_select_item;
	input i_trigger_return;
		
	output [`kNumItems-1:0] o_available_item;
	output [`kNumItems-1:0] o_output_item;
	output [`kNumCoins-1:0] o_return_coin;

	// Do not modify the values.
	wire [31:0] item_price [`kNumItems-1:0];	// Price of each item
	wire [31:0] coin_value [`kNumCoins-1:0];	// Value of each coin
	assign item_price[0] = 400;
	assign item_price[1] = 500;
	assign item_price[2] = 1000;
	assign item_price[3] = 2000;
	assign coin_value[0] = 100;
	assign coin_value[1] = 500;
	assign coin_value[2] = 1000;

	// Internal states. You may add your own net variables.
	wire [`kTotalBits-1:0] current_total;
	
	// Next internal states. You may add your own net variables.
	wire [`kTotalBits-1:0] current_total_nxt;

	
	// Variables. You may add more your own net variables.
	wire [`kTotalBits-1:0] input_total, output_total, return_total;
	wire [31:0] wait_time;


	// This module interface, structure, and given a number of modules are not mandatory but recommended.
	// However, Implementations that use modules are mandatory.
		
  	check_time_and_coin check_time_and_coin_module(.i_input_coin(i_input_coin),
  									.i_select_item(i_select_item),
									.clk(clk),
									.reset_n(reset_n),
									.o_output_item(o_output_item),
									.i_trigger_return(i_trigger_return),
									.coin_value(coin_value),
									.current_total(current_total),
									.o_return_coin(o_return_coin),
									.return_total(return_total),
									.wait_time(wait_time));

	calculate_current_state calculate_current_state_module(.i_input_coin(i_input_coin),
										.i_select_item(i_select_item),
										.item_price(item_price),
										.coin_value(coin_value),
										.current_total(current_total),
										.input_total(input_total),
										.output_total(output_total),
										.current_total_nxt(current_total_nxt),
										.o_available_item(o_available_item),
										.o_output_item(o_output_item));
	
  	change_state change_state_module(
						.clk(clk),
						.reset_n(reset_n),
						.current_total_nxt(current_total_nxt),
						.current_total(current_total));


endmodule

lab1/vending_machine/waveform.vcd
$version Generated by VerilatedVcd $end
$timescale 1ps $end
 $scope module TOP $end
  $var wire 1 * clk $end
  $var wire 1 + reset_n $end
  $var wire 3 , i_input_coin [2:0] $end
  $var wire 4 - i_select_item [3:0] $end
  $var wire 1 . i_trigger_return $end
  $var wire 4 / o_available_item [3:0] $end
  $var wire 4 0 o_output_item [3:0] $end
  $var wire 3 1 o_return_coin [2:0] $end
  $scope module vending_machine $end
   $var wire 1 * clk $end
   $var wire 1 + reset_n $end
   $var wire 3 , i_input_coin [2:0] $end
   $var wire 4 - i_select_item [3:0] $end
   $var wire 1 . i_trigger_return $end
   $var wire 4 / o_available_item [3:0] $end
   $var wire 4 0 o_output_item [3:0] $end
   $var wire 3 1 o_return_coin [2:0] $end
   $var wire 32 # item_price[0] [31:0] $end
   $var wire 32 $ item_price[1] [31:0] $end
   $var wire 32 % item_price[2] [31:0] $end
   $var wire 32 & item_price[3] [31:0] $end
   $var wire 32 ' coin_value[0] [31:0] $end
   $var wire 32 ( coin_value[1] [31:0] $end
   $var wire 32 ) coin_value[2] [31:0] $end
   $var wire 31 2 current_total [30:0] $end
   $var wire 31 3 current_total_nxt [30:0] $end
   $var wire 31 4 input_total [30:0] $end
   $var wire 31 5 output_total [30:0] $end
   $var wire 31 6 return_total [30:0] $end
   $var wire 32 7 wait_time [31:0] $end
   $scope module calculate_current_state_module $end
    $var wire 3 , i_input_coin [2:0] $end
    $var wire 4 - i_select_item [3:0] $end
    $var wire 32 # item_price[0] [31:0] $end
    $var wire 32 $ item_price[1] [31:0] $end
    $var wire 32 % item_price[2] [31:0] $end
    $var wire 32 & item_price[3] [31:0] $end
    $var wire 32 ' coin_value[0] [31:0] $end
    $var wire 32 ( coin_value[1] [31:0] $end
    $var wire 32 ) coin_value[2] [31:0] $end
    $var wire 31 2 current_total [30:0] $end
    $var wire 4 / o_available_item [3:0] $end
    $var wire 4 0 o_output_item [3:0] $end
    $var wire 31 4 input_total [30:0] $end
    $var wire 31 5 output_total [30:0] $end
    $var wire 31 3 current_total_nxt [30:0] $end
    $var wire 32 8 i [31:0] $end
   $upscope $end
   $scope module change_state_module $end
    $var wire 1 * clk $end
    $var wire 1 + reset_n $end
    $var wire 31 3 current_total_nxt [30:0] $end
    $var wire 31 2 current_total [30:0] $end
   $upscope $end
   $scope module check_time_and_coin_module $end
    $var wire 1 * clk $end
    $var wire 1 + reset_n $end
    $var wire 3 , i_input_coin [2:0] $end
    $var wire 4 - i_select_item [3:0] $end
    $var wire 4 0 o_output_item [3:0] $end
    $var wire 1 . i_trigger_return $end
    $var wire 32 ' coin_value[0] [31:0] $end
    $var wire 32 ( coin_value[1] [31:0] $end
    $var wire 32 ) coin_value[2] [31:0] $end
    $var wire 31 2 current_total [30:0] $end
    $var wire 3 1 o_return_coin [2:0] $end
    $var wire 31 6 return_total [30:0] $end
    $var wire 32 7 wait_time [31:0] $end
    $var wire 31 9 left_coin [30:0] $end
    $var wire 32 : i [31:0] $end
   $upscope $end
  $upscope $end
 $upscope $end
$enddefinitions $end


#0
b00000000000000000000000110010000 #
b00000000000000000000000111110100 $
b00000000000000000000001111101000 %
b00000000000000000000011111010000 &
b00000000000000000000000001100100 '
b00000000000000000000000111110100 (
b00000000000000000000001111101000 )
1*
0+
b010 ,
b0100 -
0.
b1111 /
b0100 0
b111 1
b1110011010110000001011000110101 2
b1110011010110000001010001000001 3
b0000000000000000000000111110100 4
b0000000000000000000001111101000 5
b1110011010110000001011000110101 6
b00000000000000000000000000000000 7
b00000000000000000000000000000100 8
b1110011010110000001010111011000 9
b11111111111111111111111111111111 :
#1
0*
1+
#2
1*
0+
b0000 /
b0000 0
b000 1
b0000000000000000000000000000000 2
b0000000000000000000000111110100 3
b0000000000000000000000000000000 5
b0000000000000000000000000000000 6
b0000000000000000000000000000000 9
#3
0*
#4
1*
1+
b000 ,
b0000 -
b0000000000000000000000000000000 3
b0000000000000000000000000000000 4
#5
0*
#6
1*
#7
0*
#8
1*
#9
0*
#10
1*
b001 ,
b0000000000000000000000001100100 2
b0000000000000000000000011001000 3
b0000000000000000000000001100100 4
b00000000000000000000000001100100 7
#11
0*
b000 ,
b0000000000000000000000001100100 3
b0000000000000000000000000000000 4
#12
1*
b001 ,
b0000000000000000000000011001000 2
b0000000000000000000000100101100 3
b0000000000000000000000001100100 4
#13
0*
b000 ,
b0000000000000000000000011001000 3
b0000000000000000000000000000000 4
#14
1*
b001 ,
b0000000000000000000000100101100 2
b0000000000000000000000110010000 3
b0000000000000000000000001100100 4
#15
0*
b000 ,
b0000000000000000000000100101100 3
b0000000000000000000000000000000 4
#16
1*
b001 ,
b0001 /
b0000000000000000000000110010000 2
b0000000000000000000000111110100 3
b0000000000000000000000001100100 4
#17
0*
b000 ,
b0000000000000000000000110010000 3
b0000000000000000000000000000000 4
#18
1*
b001 ,
b0011 /
b0000000000000000000000111110100 2
b0000000000000000000001001011000 3
b0000000000000000000000001100100 4
#19
0*
b000 ,
b0000000000000000000000111110100 3
b0000000000000000000000000000000 4
#20
1*
b001 ,
b0000000000000000000001001011000 2
b0000000000000000000001010111100 3
b0000000000000000000000001100100 4
#21
0*
b000 ,
b0000000000000000000001001011000 3
b0000000000000000000000000000000 4
#22
1*
b001 ,
b0000000000000000000001010111100 2
b0000000000000000000001100100000 3
b0000000000000000000000001100100 4
#23
0*
b000 ,
b0000000000000000000001010111100 3
b0000000000000000000000000000000 4
#24
1*
b001 ,
b0000000000000000000001100100000 2
b0000000000000000000001110000100 3
b0000000000000000000000001100100 4
#25
0*
b000 ,
b0000000000000000000001100100000 3
b0000000000000000000000000000000 4
#26
1*
b001 ,
b0000000000000000000001110000100 2
b0000000000000000000001111101000 3
b0000000000000000000000001100100 4
#27
0*
b000 ,
b0000000000000000000001110000100 3
b0000000000000000000000000000000 4
#28
1*
b001 ,
b0111 /
b0000000000000000000001111101000 2
b0000000000000000000010001001100 3
b0000000000000000000000001100100 4
#29
0*
b000 ,
b0000000000000000000001111101000 3
b0000000000000000000000000000000 4
#30
1*
b001 ,
b0000000000000000000010001001100 2
b0000000000000000000010010110000 3
b0000000000000000000000001100100 4
#31
0*
b000 ,
b0000000000000000000010001001100 3
b0000000000000000000000000000000 4
#32
1*
b001 ,
b0000000000000000000010010110000 2
b0000000000000000000010100010100 3
b0000000000000000000000001100100 4
#33
0*
b000 ,
b0000000000000000000010010110000 3
b0000000000000000000000000000000 4
#34
1*
b001 ,
b0000000000000000000010100010100 2
b0000000000000000000010101111000 3
b0000000000000000000000001100100 4
#35
0*
b000 ,
b0000000000000000000010100010100 3
b0000000000000000000000000000000 4
#36
1*
b001 ,
b0000000000000000000010101111000 2
b0000000000000000000010111011100 3
b0000000000000000000000001100100 4
#37
0*
b000 ,
b0000000000000000000010101111000 3
b0000000000000000000000000000000 4
#38
1*
b001 ,
b0000000000000000000010111011100 2
b0000000000000000000011001000000 3
b0000000000000000000000001100100 4
#39
0*
b000 ,
b0000000000000000000010111011100 3
b0000000000000000000000000000000 4
#40
1*
b001 ,
b0000000000000000000011001000000 2
b0000000000000000000011010100100 3
b0000000000000000000000001100100 4
#41
0*
b000 ,
b0000000000000000000011001000000 3
b0000000000000000000000000000000 4
#42
1*
b001 ,
b0000000000000000000011010100100 2
b0000000000000000000011100001000 3
b0000000000000000000000001100100 4
#43
0*
b000 ,
b0000000000000000000011010100100 3
b0000000000000000000000000000000 4
#44
1*
b001 ,
b0000000000000000000011100001000 2
b0000000000000000000011101101100 3
b0000000000000000000000001100100 4
#45
0*
b000 ,
b0000000000000000000011100001000 3
b0000000000000000000000000000000 4
#46
1*
b001 ,
b0000000000000000000011101101100 2
b0000000000000000000011111010000 3
b0000000000000000000000001100100 4
#47
0*
b000 ,
b0000000000000000000011101101100 3
b0000000000000000000000000000000 4
#48
1*
b001 ,
b1111 /
b0000000000000000000011111010000 2
b0000000000000000000100000110100 3
b0000000000000000000000001100100 4
#49
0*
b000 ,
b0000000000000000000011111010000 3
b0000000000000000000000000000000 4
#50
1*
b00000000000000000000000001100011 7
#51
0*
#52
1*
0+
b0000 /
b0000000000000000000000000000000 2
b0000000000000000000000000000000 3
b00000000000000000000000000000000 7
#53
0*
1+
b001 ,
b0000000000000000000000001100100 3
b0000000000000000000000001100100 4
#54
1*
b0000000000000000000000001100100 2
b0000000000000000000000011001000 3
b00000000000000000000000001100100 7
#55
0*
b000 ,
1.
b001 1
b0000000000000000000000001100100 3
b0000000000000000000000000000000 4
b0000000000000000000000001100100 6
b0000000000000000000000001100100 9
#56
1*
b00000000000000000000000001100011 7
#57
0*
#58
1*
b00000000000000000000000001100010 7
#59
0*
#60
1*
b00000000000000000000000001100001 7
#61
0*
0.
b000 1
b0000000000000000000000000000000 6
b0000000000000000000000000000000 9
#62
1*
0+
b0000000000000000000000000000000 2
b0000000000000000000000000000000 3
b00000000000000000000000000000000 7
#63
0*
1+
b010 ,
b0000000000000000000000111110100 3
b0000000000000000000000111110100 4
#64
1*
b0011 /
b0000000000000000000000111110100 2
b0000000000000000000001111101000 3
b00000000000000000000000001100100 7
#65
0*
b000 ,
1.
b010 1
b0000000000000000000000111110100 3
b0000000000000000000000000000000 4
b0000000000000000000000111110100 6
b0000000000000000000000111110100 9
#66
1*
b00000000000000000000000001100011 7
#67
0*
#68
1*
b00000000000000000000000001100010 7
#69
0*
#70
1*
b00000000000000000000000001100001 7
#71
0*
0.
b000 1
b0000000000000000000000000000000 6
b0000000000000000000000000000000 9
#72
1*
0+
b0000 /
b0000000000000000000000000000000 2
b0000000000000000000000000000000 3
b00000000000000000000000000000000 7
#73
0*
1+
b100 ,
b0000000000000000000001111101000 3
b0000000000000000000001111101000 4
#74
1*
b0111 /
b0000000000000000000001111101000 2
b0000000000000000000011111010000 3
b00000000000000000000000001100100 7
#75
0*
b000 ,
1.
b100 1
b0000000000000000000001111101000 3
b0000000000000000000000000000000 4
b0000000000000000000001111101000 6
b0000000000000000000001111101000 9
#76
1*
b00000000000000000000000001100011 7
#77
0*
#78
1*
b00000000000000000000000001100010 7
#79
0*
#80
1*
b00000000000000000000000001100001 7
#81
0*
0.
b000 1
b0000000000000000000000000000000 6
b0000000000000000000000000000000 9
#82
1*
0+
b0000 /
b0000000000000000000000000000000 2
b0000000000000000000000000000000 3
b00000000000000000000000000000000 7
#83
0*
1+
b011 ,
b0000000000000000000001001011000 3
b0000000000000000000001001011000 4
#84
1*
b0011 /
b0000000000000000000001001011000 2
b0000000000000000000010010110000 3
b00000000000000000000000001100100 7
#85
0*
b000 ,
1.
b011 1
b0000000000000000000001001011000 3
b0000000000000000000000000000000 4
b0000000000000000000001001011000 6
b0000000000000000000001001011000 9
#86
1*
b00000000000000000000000001100011 7
#87
0*
#88
1*
b00000000000000000000000001100010 7
#89
0*
#90
1*
b00000000000000000000000001100001 7
#91
0*
0.
b000 1
b0000000000000000000000000000000 6
b0000000000000000000000000000000 9
#92
1*
0+
b0000 /
b0000000000000000000000000000000 2
b0000000000000000000000000000000 3
b00000000000000000000000000000000 7
#93
0*
1+
b101 ,
b0000000000000000000010001001100 3
b0000000000000000000010001001100 4
#94
1*
b0111 /
b0000000000000000000010001001100 2
b0000000000000000000100010011000 3
b00000000000000000000000001100100 7
#95
0*
b000 ,
1.
b101 1
b0000000000000000000010001001100 3
b0000000000000000000000000000000 4
b0000000000000000000010001001100 6
b0000000000000000000010001001100 9
#96
1*
b00000000000000000000000001100011 7
#97
0*
#98
1*
b00000000000000000000000001100010 7
#99
0*
#100
1*
b00000000000000000000000001100001 7
#101
0*
0.
b000 1
b0000000000000000000000000000000 6
b0000000000000000000000000000000 9
#102
1*
0+
b0000 /
b0000000000000000000000000000000 2
b0000000000000000000000000000000 3
b00000000000000000000000000000000 7
#103
0*
1+
b110 ,
b0000000000000000000010111011100 3
b0000000000000000000010111011100 4
#104
1*
b0111 /
b0000000000000000000010111011100 2
b0000000000000000000101110111000 3
b00000000000000000000000001100100 7
#105
0*
b000 ,
1.
b110 1
b0000000000000000000010111011100 3
b0000000000000000000000000000000 4
b0000000000000000000010111011100 6
b0000000000000000000010111011100 9
#106
1*
b00000000000000000000000001100011 7
#107
0*
#108
1*
b00000000000000000000000001100010 7
#109
0*
#110
1*
b00000000000000000000000001100001 7
#111
0*
0.
b000 1
b0000000000000000000000000000000 6
b0000000000000000000000000000000 9
#112
1*
0+
b0000 /
b0000000000000000000000000000000 2
b0000000000000000000000000000000 3
b00000000000000000000000000000000 7
#113
0*
1+
b111 ,
b0000000000000000000011001000000 3
b0000000000000000000011001000000 4
#114
1*
b0111 /
b0000000000000000000011001000000 2
b0000000000000000000110010000000 3
b00000000000000000000000001100100 7
#115
0*
b000 ,
1.
b111 1
b0000000000000000000011001000000 3
b0000000000000000000000000000000 4
b0000000000000000000011001000000 6
b0000000000000000000011001000000 9
#116
1*
b00000000000000000000000001100011 7
#117
0*
#118
1*
b00000000000000000000000001100010 7
#119
0*
#120
1*
b00000000000000000000000001100001 7
#121
0*
0.
b000 1
b0000000000000000000000000000000 6
b0000000000000000000000000000000 9
#122
1*
0+
b0000 /
b0000000000000000000000000000000 2
b0000000000000000000000000000000 3
b00000000000000000000000000000000 7
#123
0*
1+
b111 ,
b0000000000000000000011001000000 3
b0000000000000000000011001000000 4
#124
1*
b0111 /
b0000000000000000000011001000000 2
b0000000000000000000110010000000 3
b00000000000000000000000001100100 7
#125
0*
b000 ,
b0000000000000000000011001000000 3
b0000000000000000000000000000000 4
#126
1*
b0110 -
b0110 0
b0000000000000000000000001100100 3
b0000000000000000000010111011100 5
#127
0*
b0000 -
b0000 0
b0000000000000000000011001000000 3
b0000000000000000000000000000000 5
#128
1*
b00000000000000000000000001100011 7
#129
0*
#130
1*
b00000000000000000000000001100010 7
#131
0*
#132
1*
b00000000000000000000000001100001 7
#133
0*
#134
1*
b00000000000000000000000001100000 7
#135
0*
#136
1*
b00000000000000000000000001011111 7
#137
0*
#138
1*
b00000000000000000000000001011110 7
#139
0*
#140
1*
b00000000000000000000000001011101 7
#141
0*
#142
1*
b00000000000000000000000001011100 7
#143
0*
#144
1*
b00000000000000000000000001011011 7
#145
0*
#146
1*
b00000000000000000000000001011010 7
#147
0*
#148
1*
b00000000000000000000000001011001 7
#149
0*
#150
1*
b00000000000000000000000001011000 7
#151
0*
#152
1*
b00000000000000000000000001010111 7
#153
0*
#154
1*
b00000000000000000000000001010110 7
#155
0*
#156
1*
b00000000000000000000000001010101 7
#157
0*
#158
1*
b00000000000000000000000001010100 7
#159
0*
#160
1*
b00000000000000000000000001010011 7
#161
0*
#162
1*
b00000000000000000000000001010010 7
#163
0*
#164
1*
b00000000000000000000000001010001 7
#165
0*
#166
1*
b00000000000000000000000001010000 7
#167
0*
#168
1*
b00000000000000000000000001001111 7
#169
0*
#170
1*
b00000000000000000000000001001110 7
#171
0*
#172
1*
b00000000000000000000000001001101 7
#173
0*
#174
1*
b00000000000000000000000001001100 7
#175
0*
#176
1*
b00000000000000000000000001001011 7
#177
0*
#178
1*
b00000000000000000000000001001010 7
#179
0*
#180
1*
b00000000000000000000000001001001 7
#181
0*
#182
1*
b00000000000000000000000001001000 7
#183
0*
#184
1*
b00000000000000000000000001000111 7
#185
0*
#186
1*
b00000000000000000000000001000110 7
#187
0*
#188
1*
b00000000000000000000000001000101 7
#189
0*
#190
1*
b00000000000000000000000001000100 7
#191
0*
#192
1*
b00000000000000000000000001000011 7
#193
0*
#194
1*
b00000000000000000000000001000010 7
#195
0*
#196
1*
b00000000000000000000000001000001 7
#197
0*
#198
1*
b00000000000000000000000001000000 7
