lab1/vending_machine/change_state.v
`include "vending_machine_def.v"


module change_state(clk,reset_n,current_total_nxt,current_total);

	input clk;
	input reset_n;
	input [`kTotalBits-1:0] current_total_nxt;
	output reg [`kTotalBits-1:0] current_total;
	
	// Sequential circuit to reset or update the states
	always @(posedge clk) begin
		if (!reset_n) begin
			// TODO: reset all states.
			current_total <= 0;
		end 
		else begin
			// TODO: update all states.
			current_total <= current_total_nxt;
		end
	end


endmodule

lab1/vending_machine/calculate_current_state.v

`include "vending_machine_def.v"
	

module calculate_current_state(i_input_coin,i_select_item,item_price,coin_value,current_total,
input_total, output_total, current_total_nxt,o_return_coin,o_available_item,o_output_item);


	
	input [`kNumCoins-1:0] i_input_coin,o_return_coin;
	input [`kNumItems-1:0]	i_select_item;			
	input [31:0] item_price [`kNumItems-1:0];
	input [31:0] coin_value [`kNumCoins-1:0];	
	input [`kTotalBits-1:0] current_total;
	output reg [`kNumItems-1:0] o_available_item,o_output_item;
	output reg  [`kTotalBits-1:0] input_total, output_total,current_total_nxt;
	
	integer i;

	always @(*) begin
		
		input_total = 0;
		o_available_item = 0;
		o_output_item = 0;
		output_total = 0;

		for(i=0; i < `kNumCoins; i = i + 1)
			input_total = input_total + i_input_coin[i] * coin_value[i];


		current_total_nxt = current_total + input_total;
	
		for(i = 0; i < `kNumItems; i = i + 1) begin

			o_available_item[i] = item_price[i] <= current_total ? 1 : 0;

			if(i_select_item[i] && o_available_item[i]) begin
				o_output_item[i] = 1;
				output_total = output_total + item_price[i];
			end	else begin
				o_output_item[i] = 0;
			end

		end 

		if(o_output_item)
			current_total_nxt = current_total - o_output_item;
		
	end

endmodule

lab1/vending_machine/check_time_and_coin.v
`include "vending_machine_def.v"

	

module check_time_and_coin(i_input_coin,i_select_item,clk,reset_n,o_output_item,i_trigger_return
,coin_value,wait_time,o_return_coin,return_total,current_total);
	input clk;
	input reset_n;
	input [`kNumCoins-1:0] i_input_coin;
	input [`kNumItems-1:0]	i_select_item;
	input [`kNumItems-1:0] o_output_item;
	input i_trigger_return;
	input [31:0] coin_value [`kNumCoins-1:0];
	input [`kTotalBits-1:0] current_total;
	output reg  [`kNumCoins-1:0] o_return_coin;
	output reg [`kTotalBits-1:0] return_total;
	output reg [31:0] wait_time;

	reg [`kTotalBits-1:0] left_coin;
	integer i;

	// initiate values
	initial begin
		// TODO: initiate values
		o_return_coin = 0;
		wait_time = 0;
	end

	always @(*) begin
		// TODO: o_return_coin
		o_return_coin = 0;
		return_total = 0;
		left_coin = 0;

		if(wait_time == 0 || i_trigger_return) begin

			return_total = current_total;
			
			for(i = 2; i >= 0; i--) begin
				
				if(current_total - left_coin >= coin_value[i]) begin
					
					o_return_coin[i] = 1;
					left_coin += (current_total - left_coin) / coin_value[i] * coin_value[i];

				end else
					o_return_coin[i] = 0;

			end
			
		end else begin
			o_return_coin = 0;
			return_total = 0;
		end
		

	end

	always @(posedge clk) begin
		if (!reset_n) begin
		// TODO: reset all states.
			wait_time = 0;
			o_return_coin = 0;
		end
		else begin
		// TODO: update all states.
			if(wait_time > 1) 
				wait_time = wait_time - 1;
			else
				wait_time = 0;
		end

		if(i_input_coin || o_output_item) begin
			wait_time = `kWaitTime;
		end

	end

endmodule

lab1/vending_machine/vending_machine.v
// Title         : vending_machine.v
// Author      : Jae-Eon Jo (Jojaeeon@postech.ac.kr) 
//			     Dongup Kwon (nankdu7@postech.ac.kr) (2015.03.30)
//			     Jaehun Ryu (jaehunryu@postech.ac.kr) (2021.03.07)

`include "vending_machine_def.v"


module vending_machine (
	clk,							// Clock signal
	reset_n,						// Reset signal (active-low)

	i_input_coin,				// coin is inserted.
	i_select_item,				// item is selected.
	i_trigger_return,			// change-return is triggered 

	o_available_item,			// Sign of the item availability
	o_output_item,			// Sign of the item withdrawal
	o_return_coin				// Sign of the coin return
);

	// Ports Declaration
	// Do not modify the module interface
	input clk;
	input reset_n;
	
	input [`kNumCoins-1:0] i_input_coin;
	input [`kNumItems-1:0] i_select_item;
	input i_trigger_return;
		
	output [`kNumItems-1:0] o_available_item;
	output [`kNumItems-1:0] o_output_item;
	output [`kNumCoins-1:0] o_return_coin;


	

	// Do not modify the values.
	wire [31:0] item_price [`kNumItems-1:0];	// Price of each item
	wire [31:0] coin_value [`kNumCoins-1:0];	// Value of each coin
	assign item_price[0] = 400;
	assign item_price[1] = 500;
	assign item_price[2] = 1000;
	assign item_price[3] = 2000;
	assign coin_value[0] = 100;
	assign coin_value[1] = 500;
	assign coin_value[2] = 1000;

	// Internal states. You may add your own net variables.
	wire [`kTotalBits-1:0] current_total;
	
	// Next internal states. You may add your own net variables.
	wire [`kTotalBits-1:0] current_total_nxt;

	
	// Variables. You may add more your own net variables.
	wire [`kTotalBits-1:0] input_total, output_total, return_total;
	wire [31:0] wait_time;


	// This module interface, structure, and given a number of modules are not mandatory but recommended.
	// However, Implementations that use modules are mandatory.
		
  	check_time_and_coin check_time_and_coin_module(.i_input_coin(i_input_coin),
  									.i_select_item(i_select_item),
									.clk(clk),
									.reset_n(reset_n),
									.o_output_item(o_output_item),
									.i_trigger_return(i_trigger_return),
									.coin_value(coin_value),
									.wait_time(wait_time),
									.o_return_coin(o_return_coin),
									.return_total(return_total),
									.current_total(current_total));

	calculate_current_state calculate_current_state_module(.i_input_coin(i_input_coin),
										.i_select_item(i_select_item),
										.item_price(item_price),
										.coin_value(coin_value),
										.current_total(current_total),
										.input_total(input_total),
										.output_total(output_total),
										.current_total_nxt(current_total_nxt),
										.o_return_coin(o_return_coin),
										.o_available_item(o_available_item),
										.o_output_item(o_output_item));
	
  	change_state change_state_module(
						.clk(clk),
						.reset_n(reset_n),
						.current_total_nxt(current_total_nxt),
						.current_total(current_total));


endmodule

lab1/vending_machine/waveform.vcd
$version Generated by VerilatedVcd $end
$timescale 1ps $end
 $scope module TOP $end
  $var wire 1 0 clk $end
  $var wire 1 1 reset_n $end
  $var wire 3 2 i_input_coin [2:0] $end
  $var wire 4 3 i_select_item [3:0] $end
  $var wire 1 4 i_trigger_return $end
  $var wire 4 5 o_available_item [3:0] $end
  $var wire 4 6 o_output_item [3:0] $end
  $var wire 3 7 o_return_coin [2:0] $end
  $scope module vending_machine $end
   $var wire 1 0 clk $end
   $var wire 1 1 reset_n $end
   $var wire 3 2 i_input_coin [2:0] $end
   $var wire 4 3 i_select_item [3:0] $end
   $var wire 1 4 i_trigger_return $end
   $var wire 4 5 o_available_item [3:0] $end
   $var wire 4 6 o_output_item [3:0] $end
   $var wire 3 7 o_return_coin [2:0] $end
   $var wire 32 # item_price[0] [31:0] $end
   $var wire 32 $ item_price[1] [31:0] $end
   $var wire 32 % item_price[2] [31:0] $end
   $var wire 32 & item_price[3] [31:0] $end
   $var wire 32 ' coin_value[0] [31:0] $end
   $var wire 32 ( coin_value[1] [31:0] $end
   $var wire 32 ) coin_value[2] [31:0] $end
   $var wire 31 8 current_total [30:0] $end
   $var wire 31 * current_total_nxt [30:0] $end
   $var wire 31 + input_total [30:0] $end
   $var wire 31 , output_total [30:0] $end
   $var wire 31 - return_total [30:0] $end
   $var wire 32 9 wait_time [31:0] $end
   $scope module calculate_current_state_module $end
    $var wire 3 2 i_input_coin [2:0] $end
    $var wire 3 7 o_return_coin [2:0] $end
    $var wire 4 3 i_select_item [3:0] $end
    $var wire 32 # item_price[0] [31:0] $end
    $var wire 32 $ item_price[1] [31:0] $end
    $var wire 32 % item_price[2] [31:0] $end
    $var wire 32 & item_price[3] [31:0] $end
    $var wire 32 ' coin_value[0] [31:0] $end
    $var wire 32 ( coin_value[1] [31:0] $end
    $var wire 32 ) coin_value[2] [31:0] $end
    $var wire 31 8 current_total [30:0] $end
    $var wire 4 5 o_available_item [3:0] $end
    $var wire 4 6 o_output_item [3:0] $end
    $var wire 31 + input_total [30:0] $end
    $var wire 31 , output_total [30:0] $end
    $var wire 31 * current_total_nxt [30:0] $end
    $var wire 32 : i [31:0] $end
   $upscope $end
   $scope module change_state_module $end
    $var wire 1 0 clk $end
    $var wire 1 1 reset_n $end
    $var wire 31 * current_total_nxt [30:0] $end
    $var wire 31 8 current_total [30:0] $end
   $upscope $end
   $scope module check_time_and_coin_module $end
    $var wire 1 0 clk $end
    $var wire 1 1 reset_n $end
    $var wire 3 2 i_input_coin [2:0] $end
    $var wire 4 3 i_select_item [3:0] $end
    $var wire 4 6 o_output_item [3:0] $end
    $var wire 1 4 i_trigger_return $end
    $var wire 32 ' coin_value[0] [31:0] $end
    $var wire 32 ( coin_value[1] [31:0] $end
    $var wire 32 ) coin_value[2] [31:0] $end
    $var wire 31 8 current_total [30:0] $end
    $var wire 3 7 o_return_coin [2:0] $end
    $var wire 31 - return_total [30:0] $end
    $var wire 32 9 wait_time [31:0] $end
    $var wire 31 . left_coin [30:0] $end
    $var wire 32 / i [31:0] $end
   $upscope $end
  $upscope $end
 $upscope $end
$enddefinitions $end


#0
b00000000000000000000000110010000 #
b00000000000000000000000111110100 $
b00000000000000000000001111101000 %
b00000000000000000000011111010000 &
b00000000000000000000000001100100 '
b00000000000000000000000111110100 (
b00000000000000000000001111101000 )
b1110011010110000001011000110001 *
b0000000000000000000000111110100 +
b0000000000000000000001111101000 ,
b1110011010110000001011000110101 -
b1110011010110000001010111011000 .
b11111111111111111111111111111111 /
10
01
b010 2
b0100 3
04
b1111 5
b0100 6
b111 7
b1110011010110000001011000110101 8
b00000000000000000000000000000000 9
b00000000000000000000000000000100 :
#1
00
11
#2
b0000000000000000000000111110100 *
b0000000000000000000000000000000 ,
b0000000000000000000000000000000 -
b0000000000000000000000000000000 .
10
01
b0000 5
b0000 6
b000 7
b0000000000000000000000000000000 8
b00000000000000000000000001100100 9
#3
00
#4
b0000000000000000000000000000000 *
b0000000000000000000000000000000 +
10
11
b000 2
b0000 3
b00000000000000000000000001100011 9
#5
00
#6
10
b00000000000000000000000001100010 9
#7
00
#8
10
b00000000000000000000000001100001 9
#9
00
#10
b0000000000000000000000011001000 *
b0000000000000000000000001100100 +
10
b001 2
b0000000000000000000000001100100 8
b00000000000000000000000001100100 9
#11
b0000000000000000000000001100100 *
b0000000000000000000000000000000 +
00
b000 2
#12
b0000000000000000000000100101100 *
b0000000000000000000000001100100 +
10
b001 2
b0000000000000000000000011001000 8
#13
b0000000000000000000000011001000 *
b0000000000000000000000000000000 +
00
b000 2
#14
b0000000000000000000000110010000 *
b0000000000000000000000001100100 +
10
b001 2
b0000000000000000000000100101100 8
#15
b0000000000000000000000100101100 *
b0000000000000000000000000000000 +
00
b000 2
#16
b0000000000000000000000111110100 *
b0000000000000000000000001100100 +
10
b001 2
b0001 5
b0000000000000000000000110010000 8
#17
b0000000000000000000000110010000 *
b0000000000000000000000000000000 +
00
b000 2
#18
b0000000000000000000001001011000 *
b0000000000000000000000001100100 +
10
b001 2
b0011 5
b0000000000000000000000111110100 8
#19
b0000000000000000000000111110100 *
b0000000000000000000000000000000 +
00
b000 2
#20
b0000000000000000000001010111100 *
b0000000000000000000000001100100 +
10
b001 2
b0000000000000000000001001011000 8
#21
b0000000000000000000001001011000 *
b0000000000000000000000000000000 +
00
b000 2
#22
b0000000000000000000001100100000 *
b0000000000000000000000001100100 +
10
b001 2
b0000000000000000000001010111100 8
#23
b0000000000000000000001010111100 *
b0000000000000000000000000000000 +
00
b000 2
#24
b0000000000000000000001110000100 *
b0000000000000000000000001100100 +
10
b001 2
b0000000000000000000001100100000 8
#25
b0000000000000000000001100100000 *
b0000000000000000000000000000000 +
00
b000 2
#26
b0000000000000000000001111101000 *
b0000000000000000000000001100100 +
10
b001 2
b0000000000000000000001110000100 8
#27
b0000000000000000000001110000100 *
b0000000000000000000000000000000 +
00
b000 2
#28
b0000000000000000000010001001100 *
b0000000000000000000000001100100 +
10
b001 2
b0111 5
b0000000000000000000001111101000 8
#29
b0000000000000000000001111101000 *
b0000000000000000000000000000000 +
00
b000 2
#30
b0000000000000000000010010110000 *
b0000000000000000000000001100100 +
10
b001 2
b0000000000000000000010001001100 8
#31
b0000000000000000000010001001100 *
b0000000000000000000000000000000 +
00
b000 2
#32
b0000000000000000000010100010100 *
b0000000000000000000000001100100 +
10
b001 2
b0000000000000000000010010110000 8
#33
b0000000000000000000010010110000 *
b0000000000000000000000000000000 +
00
b000 2
#34
b0000000000000000000010101111000 *
b0000000000000000000000001100100 +
10
b001 2
b0000000000000000000010100010100 8
#35
b0000000000000000000010100010100 *
b0000000000000000000000000000000 +
00
b000 2
#36
b0000000000000000000010111011100 *
b0000000000000000000000001100100 +
10
b001 2
b0000000000000000000010101111000 8
#37
b0000000000000000000010101111000 *
b0000000000000000000000000000000 +
00
b000 2
#38
b0000000000000000000011001000000 *
b0000000000000000000000001100100 +
10
b001 2
b0000000000000000000010111011100 8
#39
b0000000000000000000010111011100 *
b0000000000000000000000000000000 +
00
b000 2
#40
b0000000000000000000011010100100 *
b0000000000000000000000001100100 +
10
b001 2
b0000000000000000000011001000000 8
#41
b0000000000000000000011001000000 *
b0000000000000000000000000000000 +
00
b000 2
#42
b0000000000000000000011100001000 *
b0000000000000000000000001100100 +
10
b001 2
b0000000000000000000011010100100 8
#43
b0000000000000000000011010100100 *
b0000000000000000000000000000000 +
00
b000 2
#44
b0000000000000000000011101101100 *
b0000000000000000000000001100100 +
10
b001 2
b0000000000000000000011100001000 8
#45
b0000000000000000000011100001000 *
b0000000000000000000000000000000 +
00
b000 2
#46
b0000000000000000000011111010000 *
b0000000000000000000000001100100 +
10
b001 2
b0000000000000000000011101101100 8
#47
b0000000000000000000011101101100 *
b0000000000000000000000000000000 +
00
b000 2
#48
b0000000000000000000100000110100 *
b0000000000000000000000001100100 +
10
b001 2
b1111 5
b0000000000000000000011111010000 8
#49
b0000000000000000000011111010000 *
b0000000000000000000000000000000 +
00
b000 2
#50
10
b00000000000000000000000001100011 9
#51
00
#52
b0000000000000000000000000000000 *
10
01
b0000 5
b0000000000000000000000000000000 8
b00000000000000000000000000000000 9
#53
b0000000000000000000000001100100 *
b0000000000000000000000001100100 +
00
11
b001 2
#54
b0000000000000000000000011001000 *
10
b0000000000000000000000001100100 8
b00000000000000000000000001100100 9
#55
b0000000000000000000000001100100 *
b0000000000000000000000000000000 +
b0000000000000000000000001100100 -
b0000000000000000000000001100100 .
00
b000 2
14
b001 7
#56
10
b00000000000000000000000001100011 9
#57
00
#58
10
b00000000000000000000000001100010 9
#59
00
#60
10
b00000000000000000000000001100001 9
#61
b0000000000000000000000000000000 -
b0000000000000000000000000000000 .
00
04
b000 7
#62
b0000000000000000000000000000000 *
10
01
b0000000000000000000000000000000 8
b00000000000000000000000000000000 9
#63
b0000000000000000000000111110100 *
b0000000000000000000000111110100 +
00
11
b010 2
#64
b0000000000000000000001111101000 *
10
b0011 5
b0000000000000000000000111110100 8
b00000000000000000000000001100100 9
#65
b0000000000000000000000111110100 *
b0000000000000000000000000000000 +
b0000000000000000000000111110100 -
b0000000000000000000000111110100 .
00
b000 2
14
b010 7
#66
10
b00000000000000000000000001100011 9
#67
00
#68
10
b00000000000000000000000001100010 9
#69
00
#70
10
b00000000000000000000000001100001 9
#71
b0000000000000000000000000000000 -
b0000000000000000000000000000000 .
00
04
b000 7
#72
b0000000000000000000000000000000 *
10
01
b0000 5
b0000000000000000000000000000000 8
b00000000000000000000000000000000 9
#73
b0000000000000000000001111101000 *
b0000000000000000000001111101000 +
00
11
b100 2
#74
b0000000000000000000011111010000 *
10
b0111 5
b0000000000000000000001111101000 8
b00000000000000000000000001100100 9
#75
b0000000000000000000001111101000 *
b0000000000000000000000000000000 +
b0000000000000000000001111101000 -
b0000000000000000000001111101000 .
00
b000 2
14
b100 7
#76
10
b00000000000000000000000001100011 9
#77
00
#78
10
b00000000000000000000000001100010 9
#79
00
#80
10
b00000000000000000000000001100001 9
#81
b0000000000000000000000000000000 -
b0000000000000000000000000000000 .
00
04
b000 7
#82
b0000000000000000000000000000000 *
10
01
b0000 5
b0000000000000000000000000000000 8
b00000000000000000000000000000000 9
#83
b0000000000000000000001001011000 *
b0000000000000000000001001011000 +
00
11
b011 2
#84
b0000000000000000000010010110000 *
10
b0011 5
b0000000000000000000001001011000 8
b00000000000000000000000001100100 9
#85
b0000000000000000000001001011000 *
b0000000000000000000000000000000 +
b0000000000000000000001001011000 -
b0000000000000000000001001011000 .
00
b000 2
14
b011 7
#86
10
b00000000000000000000000001100011 9
#87
00
#88
10
b00000000000000000000000001100010 9
#89
00
#90
10
b00000000000000000000000001100001 9
#91
b0000000000000000000000000000000 -
b0000000000000000000000000000000 .
00
04
b000 7
#92
b0000000000000000000000000000000 *
10
01
b0000 5
b0000000000000000000000000000000 8
b00000000000000000000000000000000 9
#93
b0000000000000000000010001001100 *
b0000000000000000000010001001100 +
00
11
b101 2
#94
b0000000000000000000100010011000 *
10
b0111 5
b0000000000000000000010001001100 8
b00000000000000000000000001100100 9
#95
b0000000000000000000010001001100 *
b0000000000000000000000000000000 +
b0000000000000000000010001001100 -
b0000000000000000000010001001100 .
00
b000 2
14
b101 7
#96
10
b00000000000000000000000001100011 9
#97
00
#98
10
b00000000000000000000000001100010 9
#99
00
#100
10
b00000000000000000000000001100001 9
#101
b0000000000000000000000000000000 -
b0000000000000000000000000000000 .
00
04
b000 7
#102
b0000000000000000000000000000000 *
10
01
b0000 5
b0000000000000000000000000000000 8
b00000000000000000000000000000000 9
#103
b0000000000000000000010111011100 *
b0000000000000000000010111011100 +
00
11
b110 2
#104
b0000000000000000000101110111000 *
10
b0111 5
b0000000000000000000010111011100 8
b00000000000000000000000001100100 9
#105
b0000000000000000000010111011100 *
b0000000000000000000000000000000 +
b0000000000000000000010111011100 -
b0000000000000000000010111011100 .
00
b000 2
14
b110 7
#106
10
b00000000000000000000000001100011 9
#107
00
#108
10
b00000000000000000000000001100010 9
#109
00
#110
10
b00000000000000000000000001100001 9
#111
b0000000000000000000000000000000 -
b0000000000000000000000000000000 .
00
04
b000 7
#112
b0000000000000000000000000000000 *
10
01
b0000 5
b0000000000000000000000000000000 8
b00000000000000000000000000000000 9
#113
b0000000000000000000011001000000 *
b0000000000000000000011001000000 +
00
11
b111 2
#114
b0000000000000000000110010000000 *
10
b0111 5
b0000000000000000000011001000000 8
b00000000000000000000000001100100 9
#115
b0000000000000000000011001000000 *
b0000000000000000000000000000000 +
b0000000000000000000011001000000 -
b0000000000000000000011001000000 .
00
b000 2
14
b111 7
#116
10
b00000000000000000000000001100011 9
#117
00
#118
10
b00000000000000000000000001100010 9
#119
00
#120
10
b00000000000000000000000001100001 9
#121
b0000000000000000000000000000000 -
b0000000000000000000000000000000 .
00
04
b000 7
#122
b0000000000000000000000000000000 *
10
01
b0000 5
b0000000000000000000000000000000 8
b00000000000000000000000000000000 9
#123
b0000000000000000000011001000000 *
b0000000000000000000011001000000 +
00
11
b111 2
#124
b0000000000000000000110010000000 *
10
b0111 5
b0000000000000000000011001000000 8
b00000000000000000000000001100100 9
#125
b0000000000000000000011001000000 *
b0000000000000000000000000000000 +
00
b000 2
#126
b0000000000000000000011000110100 *
b0000000000000000000010111011100 ,
10
b0110 3
b0110 6
b0000000000000000000011000111010 8
#127
b0000000000000000000011000111010 *
b0000000000000000000000000000000 ,
00
b0000 3
b0000 6
#128
10
b00000000000000000000000001100011 9
#129
00
#130
10
b00000000000000000000000001100010 9
#131
00
#132
10
b00000000000000000000000001100001 9
#133
00
#134
10
b00000000000000000000000001100000 9
#135
00
#136
10
b00000000000000000000000001011111 9
#137
00
#138
10
b00000000000000000000000001011110 9
#139
00
#140
10
b00000000000000000000000001011101 9
#141
00
#142
10
b00000000000000000000000001011100 9
#143
00
#144
10
b00000000000000000000000001011011 9
#145
00
#146
10
b00000000000000000000000001011010 9
#147
00
#148
10
b00000000000000000000000001011001 9
#149
00
#150
10
b00000000000000000000000001011000 9
#151
00
#152
10
b00000000000000000000000001010111 9
#153
00
#154
10
b00000000000000000000000001010110 9
#155
00
#156
10
b00000000000000000000000001010101 9
#157
00
#158
10
b00000000000000000000000001010100 9
#159
00
#160
10
b00000000000000000000000001010011 9
#161
00
#162
10
b00000000000000000000000001010010 9
#163
00
#164
10
b00000000000000000000000001010001 9
#165
00
#166
10
b00000000000000000000000001010000 9
#167
00
#168
10
b00000000000000000000000001001111 9
#169
00
#170
10
b00000000000000000000000001001110 9
#171
00
#172
10
b00000000000000000000000001001101 9
#173
00
#174
10
b00000000000000000000000001001100 9
#175
00
#176
10
b00000000000000000000000001001011 9
#177
00
#178
10
b00000000000000000000000001001010 9
#179
00
#180
10
b00000000000000000000000001001001 9
#181
00
#182
10
b00000000000000000000000001001000 9
#183
00
#184
10
b00000000000000000000000001000111 9
#185
00
#186
10
b00000000000000000000000001000110 9
#187
00
#188
10
b00000000000000000000000001000101 9
#189
00
#190
10
b00000000000000000000000001000100 9
#191
00
#192
10
b00000000000000000000000001000011 9
#193
00
#194
10
b00000000000000000000000001000010 9
#195
00
#196
10
b00000000000000000000000001000001 9
#197
00
#198
10
b00000000000000000000000001000000 9
